<?xml version="1.0" encoding="utf-8"?>
<odoo>
    <data>

        <record id="view_employee_form_inherit_icomm" model="ir.ui.view">
            <field name="name">hr.employee.form.inherit.icomm</field>
            <field name="model">hr.employee</field>
            <field name="inherit_id" ref="hr.view_employee_form"/>
            <field name = "priority" eval="20" />
            <field name="arch" type="xml">
                <xpath expr="//field[@name='gender']" position="attributes">
                    <attribute name="invisible">1</attribute>
                </xpath>
                <xpath expr="//field[@name='birthday']" position="attributes">
                    <attribute name="invisible">1</attribute>
                </xpath>
                <xpath expr="//field[@name='work_email']" position="after">
                    <field name="gender"/>
                    <field name="birthday"/>
                    <field name="source_id"/>
                </xpath>
                <xpath expr="//group[@name='active_group']" position="inside">
                    <field name="joining_date"/>
                </xpath>
                <xpath expr="//separator[@name='emergency']" position="attributes">
                    <attribute name="invisible">1</attribute>
                </xpath>
                <xpath expr="//field[@name='emergency_contact']" position="attributes">
                    <attribute name="invisible">1</attribute>
                </xpath>
                <xpath expr="//field[@name='emergency_phone']" position="attributes">
                    <attribute name="invisible">1</attribute>
                </xpath>
                <xpath expr="//separator[@name='has_work_permit']" position="attributes">
                    <attribute name="invisible">1</attribute>
                </xpath>
                <xpath expr="//field[@name='visa_no']" position="attributes">
                    <attribute name="invisible">1</attribute>
                </xpath>
                <xpath expr="//field[@name='permit_no']" position="attributes">
                    <attribute name="invisible">1</attribute>
                </xpath>
                <xpath expr="//field[@name='visa_expire']" position="attributes">
                    <attribute name="invisible">1</attribute>
                </xpath>
                <xpath expr="//field[@name='work_permit_expiration_date']" position="attributes">
                    <attribute name="invisible">1</attribute>
                </xpath>
                <xpath expr="//field[@name='has_work_permit']" position="attributes">
                    <attribute name="invisible">1</attribute>
                </xpath>
                <xpath expr="//field[@name='lang']" position="attributes">
                    <attribute name="invisible">1</attribute>
                </xpath>
                <xpath expr="//div[@name='div_km_home_work']" position="attributes">
                    <attribute name="invisible">1</attribute>
                </xpath>
                <xpath expr="//button[@name='%(hr.plan_wizard_action)d']" position="attributes">
                    <attribute name="invisible">1</attribute>
                </xpath>
            </field>
        </record>

    </data>
</odoo>